tour_agent/__init__.py
tour_agent/main.py
tour_agent/dastur_kodlari/__init__.py
tour_agent/dastur_kodlari/abdumalik/__init__.py
tour_agent/dastur_kodlari/abdumalik/example.py
tour_agent/dastur_kodlari/abdumalik/list_all_tour.py
tour_agent/dastur_kodlari/asilbek/__init__.py
tour_agent-1.2.dist-info/METADATA
tour_agent-1.2.dist-info/WHEEL
tour_agent-1.2.dist-info/top_level.txt
tour_agent-1.2.dist-info/RECORD
