Metadata-Version: 2.4
Name: tour_agent
Version: 1.2
Summary: A Python library for managing tour packages and clients.
Author: Asilbek Sadullayev
Requires-Python: >=3.8
Dynamic: author
Dynamic: requires-python
Dynamic: summary
